{
  "restaurants": [
    {
      "id": 1,
      "name": "KFC",
      "email": "test@test.com",
      "address": "Gulshan 1"
    },
    {
      "name": "BFC",
      "address": "Badda, Dhaka",
      "email": "test@bfc.com",
      "id": 2
    },
    {
      "name": "GFC",
      "email": "test@test.com",
      "address": "Gulshan 2.",
      "id": 3
    },
    {
      "name": "Chillox",
      "email": "test@test.com",
      "address": "Bonani, Ahmed Tower.",
      "id": 4
    },
    {
      "name": "Sultan's Dine",
      "email": "test@bfc.com",
      "address": "Mirpur 11",
      "id": 5
    }
  ]
}